{"articles_components_icon.md":"e31c9c00","articles_advanced_cdn.md":"1703cf21","articles_develop_i18n.md":"ed14810b","articles_components_table.md":"33676e08","articles_develop_file.md":"96f7b0b1","articles_components_transition-component.md":"a058037b","articles_components_chart.md":"f40b9c8d","articles_develop_build.md":"7739d9dc","articles_develop_store.md":"8572a09a","articles_advanced_eslint.md":"7729880c","articles_components_collapse-grid.md":"70e81286","articles_develop_add-view.md":"21636195","articles_develop_style.md":"bcb1eced","index.md":"a8211f7d","articles_essentials_index.md":"ad343085","articles_develop_layout.md":"0d384e48","articles_develop_request.md":"9712ad58","articles_preparation_index.md":"e07eb98b","articles_setup_index.md":"70c877e5"}
